{
    "portfolios": [
      {
        "name": "Portfolio1",
        "cryptos":{
            "cardano":[
                {
                    "quantity": 50,
                    "pricePerCoin":0.80
                }
            ]
        }
      },
      {
        "name": "Portfolio2",
        "cryptos":{
            "cardano":[
                {
                    "quantity": 50,
                    "pricePerCoin":0.80
                }
            
            ],
            "ethereum":[
                {
                    "quantity": 2,
                    "pricePerCoin":3000
                }
            ]
        }
      }
      
    ]
}